pack2534/__init__.py
pack2534/funcs.py
pack2534-0.0.1.dist-info/METADATA
pack2534-0.0.1.dist-info/WHEEL
pack2534-0.0.1.dist-info/top_level.txt
pack2534-0.0.1.dist-info/RECORD
